{
  "loading": "Đang tải...",
  "connecting": "Đang kết nối...",
  "connectionTimeout": "Hết thời gian kết nối",
  "networkError": "Lỗi mạng",
  "parseError": "Lỗi phân tích dữ liệu",
  "footer": "Phiên bản {0} | Thiết bị {1}",
  "connecting_auth": "Đang kết nối đến máy chủ xác thực...",
  "launching_game": "Đang khởi chạy trò chơi...",
  "auth_failed": "Xác thực thất bại: {0}",
  "checking_version": "Đang kiểm tra phiên bản...",
  "version_check_failed": "Kiểm tra phiên bản thất bại: {0}",
  "comparing_resources": "Đang so sánh tài nguyên...",
  "resource_check_failed": "Kiểm tra tài nguyên thất bại",
  "resources_updated": "Tài nguyên đã cập nhật",
  "start_downloading": "Bắt đầu tải xuống...",
  "downloading_resources": "Đang tải {0} / {1}",
  "unpacking_resources": "Đang giải nén {0}%",
  "download_complete": "Tải xuống hoàn tất",
  "download_failed": "Tải xuống thất bại",
  "loading_metadata": "Đang tải dữ liệu meta...",
  "metadata_load_failed": "Tải dữ liệu meta thất bại",
  "launch_failed": "Khởi động thất bại: {0}",
  "resourceHp": "HP",
  "resourceMp": "MP",
  "resourceLp": "Thể lực",
  "channelSystem": "Hệ thống",
  "channelPrivate": "Riêng",
  "channelLocal": "Địa phương",
  "channelBattle": "Chiến đấu",
  "channelBroadcast": "Chung",
  "channelRumor": "Tin đồn",
  "channelAutomation": "Tự động",
  "chatPlaceholder": "Nhập tin nhắn...",
  "filterAll": "Tất cả"
}